<?xml version="1.0" encoding="utf-8" ?>
<dwsync>
<file name="index.html" server="9levens.nl" local="131047671160778461" remote="131020239600000000" Dst="2" />
<file name="stammbaum_alonso.html" server="9levens.nl" local="131047671160943564" remote="130126104000000000" Dst="2" />
<file name="stammbaum_andrassy.html" server="9levens.nl" local="131047671161667144" remote="130126104000000000" Dst="2" />
<file name="stammbaum_astor.html" server="9levens.nl" local="131047671162142888" remote="130126104000000000" Dst="2" />
<file name="stammbaum_arcania.html" server="9levens.nl" local="131047671162303017" remote="130126104000000000" Dst="2" />
<file name="stammbaum_coja.html" server="9levens.nl" local="131047671163030616" remote="130126104000000000" Dst="2" />
<file name="stammbaum_domino.html" server="9levens.nl" local="131047671163678151" remote="130126104000000000" Dst="2" />
<file name="stammbaum_guinevere.html" server="9levens.nl" local="131047671163874814" remote="130126104000000000" Dst="2" />
<file name="stammbaum_ismene.html" server="9levens.nl" local="131047671164333608" remote="130126104000000000" Dst="2" />
<file name="stammbaum_jacky.html" server="9levens.nl" local="131047671164880377" remote="130126104000000000" Dst="2" />
<file name="stammbaum_karl.html" server="9levens.nl" local="131047671165190608" remote="130126104000000000" Dst="2" />
<file name="stammbaum_karma.html" server="9levens.nl" local="131047671165305486" remote="130126104000000000" Dst="2" />
<file name="stammbaum_lisamarie.html" server="9levens.nl" local="131047671166117468" remote="130126104000000000" Dst="2" />
<file name="stammbaum_pomona.html" server="9levens.nl" local="131047671166287813" remote="130126104000000000" Dst="2" />
<file name="stammbaum_neville.html" server="9levens.nl" local="131047671166583438" remote="130126104000000000" Dst="2" />
</dwsync>